uoft_aruba/__init__.py
uoft_aruba/cpsec_whitelist.py
uoft_aruba-1.0.1.dist-info/METADATA
uoft_aruba-1.0.1.dist-info/WHEEL
uoft_aruba-1.0.1.dist-info/entry_points.txt
uoft_aruba-1.0.1.dist-info/RECORD
