Metadata-Version: 2.1
Name: uoft_aruba
Version: 1.0.1
Summary: Collection of utilities for interacting with Aruba infrastructure
Project-URL: Repository, https://github.com/uoft-networking/tools
Author-email: Kyle Fozo <kyle.fozo@utoronto.ca>, University of Toronto Governing Council <governing.council@utoronto.ca>
License: MIT
Requires-Python: >=3.10
Requires-Dist: pydantic[dotenv]
Requires-Dist: typer
Requires-Dist: uoft-core
